waiter/__init__.py
waiter/py.typed
waiter-1.4.dist-info/LICENSE.txt
waiter-1.4.dist-info/METADATA
waiter-1.4.dist-info/WHEEL
waiter-1.4.dist-info/top_level.txt
waiter-1.4.dist-info/RECORD
